evargs/__init__.py
evargs/evargs.py
evargs/exception.py
evargs/exp_evargs.py
evargs/helper.py
evargs/list_formatter.py
evargs/modules.py
evargs/type_cast.py
evargs/validator.py
evargs-1.0.0.dist-info/licenses/LICENSE.md
evargs-1.0.0.dist-info/METADATA
evargs-1.0.0.dist-info/WHEEL
evargs-1.0.0.dist-info/top_level.txt
evargs-1.0.0.dist-info/RECORD
