Metadata-Version: 2.4
Name: evargs
Version: 1.0.0
Summary: "EvArgs" is a Python module designed for value assignment, easy expression parsing, and type casting. It validates values based on defined rules and offers flexible configuration along with custom validation methods.
Home-page: https://github.com/deer-hunt/evargs
Author: deer-hunt
License: MIT
Project-URL: Documentation, https://deer-hunt.github.io/evargs/
Project-URL: Github, https://github.com/deer-hunt/evargs/
Project-URL: Changelog, https://github.com/deer-hunt/evargs/blob/main/CHANGELOG.md
Keywords: args,argument,evaluate,evaluation,argparse,condition,parameter,validator,validation,cast,casting,type-cast,assign,assignment,customize,expression
Classifier: Development Status :: 5 - Production/Stable
Classifier: Intended Audience :: Developers
Classifier: Intended Audience :: System Administrators
Classifier: Intended Audience :: Information Technology
Classifier: Intended Audience :: Science/Research
Classifier: Intended Audience :: Telecommunications Industry
Classifier: Programming Language :: Python :: 3
Classifier: Programming Language :: Python :: 3.6
Classifier: Programming Language :: Python :: 3.7
Classifier: Programming Language :: Python :: 3.8
Classifier: Programming Language :: Python :: 3.9
Classifier: Programming Language :: Python :: 3.10
Classifier: Programming Language :: Python :: 3.11
Classifier: Programming Language :: Python :: 3.12
Classifier: Programming Language :: Python :: 3.13
Classifier: License :: OSI Approved :: MIT License
Classifier: Operating System :: OS Independent
Classifier: Topic :: Software Development :: Libraries :: Python Modules
Requires-Python: >=3.6
License-File: LICENSE.md
Dynamic: license-file
